uma/JSONable.py
uma/__init__.py
uma/currency.py
uma/exceptions.py
uma/kyc_status.py
uma/payer_data.py
uma/protocol.py
uma/public_key_cache.py
uma/uma.py
uma/uma_invoice_creator.py
uma/version.py
uma_sdk-0.1.5.dist-info/METADATA
uma_sdk-0.1.5.dist-info/WHEEL
uma_sdk-0.1.5.dist-info/top_level.txt
uma_sdk-0.1.5.dist-info/RECORD
