Metadata-Version: 2.1
Name: uma-sdk
Version: 0.1.5
Summary: Python SDK for UMA (universal money address)
Author: Lightspark Group, Inc.
Author-email: info@lightspark.com
License: Apache-2.0
Project-URL: Documentation, https://app.lightspark.com/docs/uma-sdk/introduction
Project-URL: Source Code, https://github.com/uma-universal-money-address/uma-python-sdk/
Requires-Dist: cryptography
Requires-Dist: eciespy
Requires-Dist: requests
